vehiclepass/__init__.py
vehiclepass/_types.py
vehiclepass/constants.py
vehiclepass/doors.py
vehiclepass/errors.py
vehiclepass/indicators.py
vehiclepass/tire_pressure.py
vehiclepass/units.py
vehiclepass/vehicle.py
vehiclepass-0.3.0.dist-info/METADATA
vehiclepass-0.3.0.dist-info/WHEEL
vehiclepass-0.3.0.dist-info/licenses/LICENSE
vehiclepass-0.3.0.dist-info/RECORD
