Metadata-Version: 2.4
Name: vehiclepass
Version: 0.3.0
Summary: A Python API to manage your FordPass-enabled vehicle.
Project-URL: Homepage, https://github.com/austind/vehiclepass
Project-URL: Repository, https://github.com/austind/vehiclepass.git
Project-URL: Issues, https://github.com/austind/vehiclepass/issues
Project-URL: Changelog, https://github.com/austind/vehiclepass/blob/main/CHANGELOG.md
Author-email: Austin de Coup-Crank <austindcc@gmail.com>
License-File: LICENSE
Classifier: Development Status :: 4 - Beta
Classifier: Intended Audience :: Developers
Classifier: License :: OSI Approved :: The Unlicense (Unlicense)
Classifier: Operating System :: OS Independent
Classifier: Programming Language :: Python :: 3
Classifier: Programming Language :: Python :: 3.9
Classifier: Programming Language :: Python :: 3.10
Classifier: Programming Language :: Python :: 3.11
Classifier: Programming Language :: Python :: 3.12
Classifier: Programming Language :: Python :: 3.13
Classifier: Topic :: Software Development :: Libraries :: Python Modules
Requires-Python: >=3.9
Requires-Dist: httpx>=0.28.1
Requires-Dist: pydantic>=2.11.1
Requires-Dist: python-dotenv>=1.1.0
